{"title":"GeekNews ─ 최신글","url":"https://news.hada.io/new","favicon":"https://news.hada.io/favicon.ico","elements":[{"title":"xguru","contents":"<span id=\"tp7193\">16</span> points by <a href=\"/user?id=xguru\">xguru</a> 10시간전<span id=\"unvote7193\"></span> | <a href=\"topic?id=7193\" class=\"u\">댓글 5개</a>","link":"https://news.hada.io/topic?id=7193","retrieved":1660621388676},{"title":"xguru","contents":"<span id=\"tp7192\">5</span> points by <a href=\"/user?id=xguru\">xguru</a> 11시간전<span id=\"unvote7192\"></span> | <a href=\"topic?id=7192\" class=\"u\">댓글 1개</a>","link":"https://news.hada.io/topic?id=7192","retrieved":1660613260595},{"title":"ganadist","contents":"<span id=\"tp7191\">5</span> points by <a href=\"/user?id=ganadist\">ganadist</a> 12시간전<span id=\"unvote7191\"></span> | <a href=\"topic?id=7191\" class=\"u\">댓글 2개</a>","link":"https://news.hada.io/topic?id=7191","retrieved":1660613260595},{"title":"xguru","contents":"<span id=\"tp7190\">4</span> points by <a href=\"/user?id=xguru\">xguru</a> 12시간전<span id=\"unvote7190\"></span> | <a href=\"topic?id=7190\" class=\"u\">댓글 1개</a>","link":"https://news.hada.io/topic?id=7190","retrieved":1660613260595},{"title":"xguru","contents":"<span id=\"tp7189\">6</span> points by <a href=\"/user?id=xguru\">xguru</a> 12시간전<span id=\"unvote7189\"></span> | <a href=\"topic?id=7189\" class=\"u\">댓글 5개</a>","link":"https://news.hada.io/topic?id=7189","retrieved":1660613260601},{"title":"xguru","contents":"<span id=\"tp7188\">16</span> points by <a href=\"/user?id=xguru\">xguru</a> 12시간전<span id=\"unvote7188\"></span> | <a href=\"topic?id=7188\" class=\"u\">댓글 1개</a>","link":"https://news.hada.io/topic?id=7188","retrieved":1660613260601},{"title":"luckydaun","contents":"<span id=\"tp7187\">16</span> points by <a href=\"/user?id=luckydaun\">luckydaun</a> 1일전<span id=\"unvote7187\"></span> | <a href=\"topic?id=7187\" class=\"u\">댓글과 토론</a>","link":"https://news.hada.io/topic?id=7187","retrieved":1660547646253},{"title":"xguru","contents":"<span id=\"tp7186\">7</span> points by <a href=\"/user?id=xguru\">xguru</a> 1일전<span id=\"unvote7186\"></span> | <a href=\"topic?id=7186\" class=\"u\">댓글과 토론</a>","link":"https://news.hada.io/topic?id=7186","retrieved":1660535706710},{"title":"xguru","contents":"<span id=\"tp7185\">17</span> points by <a href=\"/user?id=xguru\">xguru</a> 1일전<span id=\"unvote7185\"></span> | <a href=\"topic?id=7185\" class=\"u\">댓글과 토론</a>","link":"https://news.hada.io/topic?id=7185","retrieved":1660526585583},{"title":"xguru","contents":"<span id=\"tp7184\">30</span> points by <a href=\"/user?id=xguru\">xguru</a> 1일전<span id=\"unvote7184\"></span> | <a href=\"topic?id=7184\" class=\"u\">댓글 5개</a>","link":"https://news.hada.io/topic?id=7184","retrieved":1660526585583},{"title":"xguru","contents":"<span id=\"tp7183\">26</span> points by <a href=\"/user?id=xguru\">xguru</a> 1일전<span id=\"unvote7183\"></span> | <a href=\"topic?id=7183\" class=\"u\">댓글 2개</a>","link":"https://news.hada.io/topic?id=7183","retrieved":1660526585585},{"title":"xguru","contents":"<span id=\"tp7182\">35</span> points by <a href=\"/user?id=xguru\">xguru</a> 2일전<span id=\"unvote7182\"></span> | <a href=\"topic?id=7182\" class=\"u\">댓글 3개</a>","link":"https://news.hada.io/topic?id=7182","retrieved":1660526585585},{"title":"xguru","contents":"<span id=\"tp7181\">3</span> points by <a href=\"/user?id=xguru\">xguru</a> 2일전<span id=\"unvote7181\"></span> | <a href=\"topic?id=7181\" class=\"u\">댓글 1개</a>","link":"https://news.hada.io/topic?id=7181","retrieved":1660439967491},{"title":"xguru","contents":"<span id=\"tp7180\">15</span> points by <a href=\"/user?id=xguru\">xguru</a> 2일전<span id=\"unvote7180\"></span> | <a href=\"topic?id=7180\" class=\"u\">댓글 1개</a>","link":"https://news.hada.io/topic?id=7180","retrieved":1660439967500},{"title":"xguru","contents":"<span id=\"tp7179\">6</span> points by <a href=\"/user?id=xguru\">xguru</a> 3일전<span id=\"unvote7179\"></span> | <a href=\"topic?id=7179\" class=\"u\">댓글과 토론</a>","link":"https://news.hada.io/topic?id=7179","retrieved":1660439967500},{"title":"sheriffgambino","contents":"<span id=\"tp7178\">8</span> points by <a href=\"/user?id=sheriffgambino\">sheriffgambino</a> 3일전<span id=\"unvote7178\"></span> | <a href=\"topic?id=7178\" class=\"u\">댓글 1개</a>","link":"https://news.hada.io/topic?id=7178","retrieved":1660432466938},{"title":"xguru","contents":"<span id=\"tp7177\">18</span> points by <a href=\"/user?id=xguru\">xguru</a> 3일전<span id=\"unvote7177\"></span> | <a href=\"topic?id=7177\" class=\"u\">댓글과 토론</a>","link":"https://news.hada.io/topic?id=7177","retrieved":1660360686155},{"title":"xguru","contents":"<span id=\"tp7176\">9</span> points by <a href=\"/user?id=xguru\">xguru</a> 3일전<span id=\"unvote7176\"></span> | <a href=\"topic?id=7176\" class=\"u\">댓글 1개</a>","link":"https://news.hada.io/topic?id=7176","retrieved":1660353007689},{"title":"xguru","contents":"<span id=\"tp7175\">12</span> points by <a href=\"/user?id=xguru\">xguru</a> 4일전<span id=\"unvote7175\"></span> | <a href=\"topic?id=7175\" class=\"u\">댓글 3개</a>","link":"https://news.hada.io/topic?id=7175","retrieved":1660353007689},{"title":"xguru","contents":"<span id=\"tp7174\">5</span> points by <a href=\"/user?id=xguru\">xguru</a> 4일전<span id=\"unvote7174\"></span> | <a href=\"topic?id=7174\" class=\"u\">댓글과 토론</a>","link":"https://news.hada.io/topic?id=7174","retrieved":1660353007695}]}