{"title":"GeekNews ─ 원문","url":"https://news.hada.io/","favicon":"https://news.hada.io/favicon.ico","elements":[{"title":"GraphQL은 좀 짜증나요","contents":"(news.ycombinator.com)","link":"https://news.ycombinator.com/item?id=32366759","retrieved":1660008296275},{"title":"mCaptcha - PoW 기반의 무료 캡차 오픈소스","contents":"(github.com/mCaptcha)","link":"https://github.com/mCaptcha/mCaptcha","retrieved":1660008296275},{"title":"MidJourney - SF에 강점을 가진 이미지 생성 AI","contents":"(midjourney.com)","link":"https://www.midjourney.com/","retrieved":1660008296275},{"title":"Firefox Translations - 오프라인으로 동작하는 공식 번역 애드온","contents":"(addons.mozilla.org)","link":"https://addons.mozilla.org/ko/firefox/addon/firefox-translations/","retrieved":1660016518201},{"title":"스패머들을 암호 지옥으로 보내기","contents":"(troyhunt.com)","link":"https://www.troyhunt.com/sending-spammers-to-password-purgatory-with-microsoft-power-automate-and-cloudflare-workers-kv/","retrieved":1660008296275},{"title":"딥페이크 비디오 통화인지 알려면 고개를 돌려보라고 하세요","contents":"(metaphysic.ai)","link":"https://metaphysic.ai/to-uncover-a-deepfake-video-call-ask-the-caller-to-turn-sideways/","retrieved":1660016518203},{"title":"당신은 아마도 잘못된 사전을 사용하고 있을 겁니다","contents":"(jsomers.net)","link":"http://jsomers.net/blog/dictionary","retrieved":1659929873162},{"title":"Show GN: 10만 전자: 쿠팡에서 10만원 넘는 전자제품 가격을 추적합니다.","contents":"(junja10.com)","link":"https://news.hada.io/topic?id=7142","retrieved":1659961763198},{"title":"Product Market Fit은 어떤 느낌일까?","contents":"(mostlymetrics.com)","link":"https://www.mostlymetrics.com/p/what-product-market-fit-feels-like","retrieved":1659921502466},{"title":"저물어가는 소셜 네트워크의 시대 (번역)","contents":"(ebadak.news)","link":"https://ebadak.news/2022/08/05/sunset-social-network-facebook-tiktok/","retrieved":1660026029794},{"title":"내가 Wordnote 사전 앱을 만든 이유","contents":"(wordnote.app)","link":"https://www.wordnote.app/blog/why-i-built-dictionary-app","retrieved":1659921502469},{"title":"왜 인류는 1960년대처럼 강력한 로켓을 발사하지 못할까?","contents":"(facebook.com)","link":"https://www.facebook.com/100001843848045/posts/pfbid04L5P5iNcDBe1DBgFAKeNbzmHPjvheCXycNEqp5YzhBwA5JnW3HEkyfmH8VbKg6Gxl/","retrieved":1659929873161},{"title":"Andrew Chen - How to design a referral program","contents":"(ugong2san.tistory.com)","link":"https://ugong2san.tistory.com/4529","retrieved":1660016518209},{"title":"SQLite-zstd - 랜덤억세스 가능한 Row 레벨 압축 확장","contents":"(github.com/phiresky)","link":"https://github.com/phiresky/sqlite-zstd","retrieved":1659921502469},{"title":"GitLab은 직원 노트북에 Microsoft Windows 사용을 금지하고 있음","contents":"(about.gitlab.com)","link":"https://about.gitlab.com/handbook/business-technology/team-member-enablement/onboarding-access-requests/#laptop-configurations","retrieved":1659835430604},{"title":"js1024 우승자 발표, 1등은 강성훈님의 epyt","contents":"(js1024.fun)","link":"https://js1024.fun/results/2022","retrieved":1659755858632},{"title":"TensorDock - 저렴한 GPU 클라우드 ($0.29/hr)","contents":"(tensordock.com)","link":"https://www.tensordock.com/","retrieved":1659835430604},{"title":"AWS Lambda, 계층형(Tiered) 요금제 발표","contents":"(aws.amazon.com)","link":"https://aws.amazon.com/ko/blogs/compute/introducing-tiered-pricing-for-aws-lambda/","retrieved":1659921502469},{"title":"Weights & Biases - 머신러닝 실험 시각화 & 트래킹 도구","contents":"(github.com/wandb)","link":"https://github.com/wandb/wandb","retrieved":1659748334485},{"title":"어려운 한글 웹폰트 최적화, 꼼수로 해결하기","contents":"(velog.io)","link":"https://velog.io/@filekiwi/optimization-web-font-hangul-part-2","retrieved":1659677434853}]}