{"title":"GeekNews ─ 원문","url":"https://news.hada.io/","favicon":"https://news.hada.io/favicon.ico","elements":[{"title":"리소스의 ID, GUID로 할까 Sequential로 할까?","contents":"(twitter.com/dylayed)","link":"https://twitter.com/dylayed/status/1496020581610778625","retrieved":1645640073224},{"title":"Tally Forms - 무료 TypeForm 대체제","contents":"(tally.so)","link":"https://tally.so/","retrieved":1645582062839},{"title":"가장 빠른 GIF는 존재하지 않음","contents":"(biphelps.com)","link":"https://www.biphelps.com/blog/The-Fastest-GIF-Does-Not-Exist","retrieved":1645577844632},{"title":"Waifu Labs V2 - AI가 그리며 커스텀 가능한 일본 애니메이션 스타일 그림 생성기","contents":"(waifulabs.com)","link":"https://waifulabs.com/blog/ai-creativity","retrieved":1645593213799},{"title":"Flutter가 가장 인기 있는 크로스 플랫폼 모바일 SDK인 이유","contents":"(stackoverflow.blog)","link":"https://stackoverflow.blog/2022/02/21/why-flutter-is-the-most-popular-cross-platform-mobile-sdk/","retrieved":1645577844632},{"title":"예전엔 엄청 어려웠지만, 지금은 쉬워진 것들","contents":"(jvns.ca)","link":"https://jvns.ca/blog/2022/02/20/things-that-used-to-be-hard-and-are-now-easy/","retrieved":1645410551051},{"title":"구글 검색이 죽어가고 있다","contents":"(dkb.io)","link":"https://dkb.io/post/google-search-is-dying","retrieved":1645424242916},{"title":"페이스북은 저소득 국가들의 인터넷 접속을 돕고 있을까?","contents":"(technologyreview.kr)","link":"https://www.technologyreview.kr/%ED%8E%98%EC%9D%B4%EC%8A%A4%EB%B6%81%EC%9D%80-%EC%A0%80%EC%86%8C%EB%93%9D-%EA%B5%AD%EA%B0%80%EB%93%A4%EC%9D%98-%EC%9D%B8%ED%84%B0%EB%84%B7-%EC%A0%91%EC%86%8D%EC%9D%84-%EB%8F%95%EA%B3%A0-%EC%9E%88/","retrieved":1645582062839},{"title":"Grist - Airtable과 Google Sheet의 오픈소스 대체제","contents":"(github.com/gristlabs)","link":"https://github.com/gristlabs/grist-core","retrieved":1645490996484},{"title":"Show GN: K-Startup 사업공고 알림 슬랙 봇","contents":"(startup-notify.web.app)","link":"https://news.hada.io/topic?id=6035","retrieved":1645586107473},{"title":"[공식한글] 넷플릭스 문화, 가치관","contents":"(jobs.netflix.com)","link":"https://jobs.netflix.com/culture?lang=%ED%95%9C%EA%B5%AD%EC%96%B4","retrieved":1645420380150},{"title":"Fred's ImageMagick Scripts","contents":"(fmwconcepts.com)","link":"http://www.fmwconcepts.com/imagemagick/crossprocess/index.php","retrieved":1645408692647},{"title":"구글, 첫 페이지 하단에 위젯 포함하는 테스트 중","contents":"(9to5google.com)","link":"https://9to5google.com/2022/02/16/google-search-widgets/","retrieved":1645577844632},{"title":"Chris Lattner가 Swift Core팀을 떠남","contents":"(forums.swift.org)","link":"https://forums.swift.org/t/core-team-to-form-language-workgroup/55455","retrieved":1645497063843},{"title":"Roboto Serif 폰트 공개","contents":"(material.io)","link":"https://material.io/blog/roboto-serif","retrieved":1645495142170},{"title":"Jujutsu - 간단하고 강력한 Git 호환 DVCS","contents":"(github.com/martinvonz)","link":"https://github.com/martinvonz/jj","retrieved":1645408692649},{"title":"I was wrong, we need crypto","contents":"(world.hey.com)","link":"https://world.hey.com/dhh/i-was-wrong-we-need-crypto-587ccb03","retrieved":1645460348118},{"title":"Judyrecords - 무료 미국 법원 사건 및 소송 검색 시스템","contents":"(judyrecords.com)","link":"https://www.judyrecords.com/","retrieved":1645408692656},{"title":"Griffel - 미리 컴파일 가능한 CSS-in-JS","contents":"(github.com/microsoft)","link":"https://github.com/microsoft/griffel","retrieved":1645495142163},{"title":"자바스크립트 빌드 & 번들러 툴인 vite 문서를 번역했어요","contents":"(vitejs-kr.github.io)","link":"https://vitejs-kr.github.io/","retrieved":1645254745886}]}