{"title":"GeekNews ─ 원문","url":"https://news.hada.io/","favicon":"https://news.hada.io/favicon.ico","elements":[{"title":"Spotify와 구글, 결제 방식을 선택할 수 있는 User Choice Billing 발표","contents":"(newsroom.spotify.com)","link":"https://newsroom.spotify.com/2022-03-23/spotify-and-google-announce-user-choice-billing/","retrieved":1648083592536},{"title":"Mitmproxy 8 릴리즈","contents":"(mitmproxy.org)","link":"https://mitmproxy.org/posts/releases/mitmproxy8/","retrieved":1648083592564},{"title":"Java 18 / JDK 18 : General Availability","contents":"(mail.openjdk.java.net)","link":"https://mail.openjdk.java.net/pipermail/jdk-dev/2022-March/006458.html","retrieved":1648083592564},{"title":"2022 AI Index Report","contents":"(aiindex.stanford.edu)","link":"https://aiindex.stanford.edu/report/","retrieved":1648083592564},{"title":"예제로 배우는 Deno","contents":"(examples.deno.land)","link":"https://examples.deno.land/","retrieved":1647916417901},{"title":"웹 개발자의 비밀무기들","contents":"(twitter.com/keif_xyz)","link":"https://twitter.com/keif_xyz/status/1499402265341296642","retrieved":1647829625888},{"title":"기술 창업자들의 고객지원 실수와 해결책들","contents":"(twitter.com/louisnicholls_)","link":"https://twitter.com/louisnicholls_/status/1505231211391770630","retrieved":1647910776889},{"title":"벤츠, 자율운전중 사고시 법적 책임을 지겠다고 밝혀","contents":"(roadandtrack.com)","link":"https://www.roadandtrack.com/news/a39481699/what-happens-if-mercedes-drivepilot-causes-a-crash/","retrieved":1648004047983},{"title":"35년간의 뉴스레터 운영에서 얻은 경험들","contents":"(cjchilvers.com)","link":"https://www.cjchilvers.com/blog/35-lessons-from-35-years-of-newsletter-publishing","retrieved":1647829625889},{"title":"CotEditor - macOS용 오픈소스 텍스트 에디터","contents":"(coteditor.com)","link":"https://coteditor.com/","retrieved":1647916417905},{"title":"VRoom - 하이엔드 RISC-V 구현체 오픈소스","contents":"(github.com/MoonbaseOtago)","link":"https://github.com/MoonbaseOtago/vroom","retrieved":1648004047971},{"title":"Lapsus$ 해킹그룹, Okta를 해킹했다고 주장","contents":"(theverge.com)","link":"https://www.theverge.com/2022/3/22/22990637/okta-breach-single-sign-on-lapsus-hacker-group","retrieved":1647997489359},{"title":"오픈소스의 무기화에 대해","contents":"(beny23.github.io)","link":"https://beny23.github.io/posts/on_weaponisation_of_open_source/","retrieved":1647829625876},{"title":"AWS Cloud Quest 공개 - 클라우드 기술 교육용 온라인 RPG","contents":"(skillbuilder.aws)","link":"https://skillbuilder.aws/cloudquest","retrieved":1647926012806},{"title":"Next.js 공식 'Foundations' 코스 공개","contents":"(nextjs.org)","link":"https://nextjs.org/learn/foundations/about-nextjs","retrieved":1647829625883},{"title":"NVIDIA, Hopper 아키텍처의 H100 GPU 발표","contents":"(nvidianews.nvidia.com)","link":"https://nvidianews.nvidia.com/news/nvidia-announces-hopper-architecture-the-next-generation-of-accelerated-computing","retrieved":1648006139442},{"title":"dav1d 1.0.0 릴리즈 - 오픈소스 크로스플랫폼 AV1 디코더","contents":"(code.videolan.org)","link":"https://code.videolan.org/videolan/dav1d/-/blob/1.0.0/NEWS","retrieved":1647910776895},{"title":"Lapsus$, Microsoft의 소스코드와 LG 계정 해쉬 덤프도 훔쳤다고 밝혀","contents":"(pcgamer.com)","link":"https://www.pcgamer.com/hacking-group-lapsusdollar-leaks-microsoft-source-code-and-lg-accounts/","retrieved":1647997489359},{"title":"OpenBSD/Arm64를 애플 M1 에서 동작 성공","contents":"(marc.info)","link":"https://marc.info/?l=openbsd-arm&m=164768992119719&w=2","retrieved":1647997489361},{"title":"[ 번역글 ] ECMAScript 스펙을 읽는 법","contents":"(somedaycode.tistory.com)","link":"https://somedaycode.tistory.com/m/5","retrieved":1647688367908}]}