{"title":"GeekNews Show","url":"https://news.hada.io/show","favicon":"https://news.hada.io/favicon.ico","elements":[{"title":"Show GN: BakingSheet - Unity/C# 게임 기획 데이터를 위한 스프레드시트 스키마 작성 및 포맷 변환 도구","contents":"(github.com/cathei)","link":"https://news.hada.io/topic?id=7245","retrieved":1661236127586},{"title":"Show GN: 10만 전자: 쿠팡에서 10만원 넘는 전자제품 가격을 추적합니다.","contents":"(junja10.com)","link":"https://news.hada.io/topic?id=7142","retrieved":1659961773513},{"title":"Show GN: 리그오브레전드 전적 알림 앱","contents":"(apps.apple.com)","link":"https://news.hada.io/topic?id=7223","retrieved":1660983565471},{"title":"Show GN: epyt: 1KB 타자 게임","contents":"(js1024.fun)","link":"https://news.hada.io/topic?id=6967","retrieved":1657719559741},{"title":"Show GN: Chollian Wallpaper : 실시간 위성 사진 배경화면 앱","contents":"(github.com/pjessesco)","link":"https://news.hada.io/topic?id=7040","retrieved":1658744273676},{"title":"Show GN: 사이드프로젝트/창업 팀빌딩 플랫폼","contents":"(disquiet.io)","link":"https://news.hada.io/topic?id=6835","retrieved":1656069153823},{"title":"Show GN: ApplePie Pro 2.0 - Notion MVP였는데 토이 프로젝트가 아니라 진심 100%","contents":"(applepie.pro)","link":"https://news.hada.io/topic?id=6866","retrieved":1656477819663},{"title":"Show GN: 트위터 연동 자유시장","contents":"(applepie.pro)","link":"https://news.hada.io/topic?id=6901","retrieved":1656976464724},{"title":"Show GN: 블록체인 개발자를 위한 온라인 저지 사이트","contents":"(app.web3oj.com)","link":"https://news.hada.io/topic?id=6852","retrieved":1656346876559},{"title":"Show GN: 모두를 위한 소셜 링크 사이트","contents":"(linktag.org)","link":"https://news.hada.io/topic?id=6927","retrieved":1657165578070},{"title":"Show GN: 당신의 트위터 감정사전 <beta>","contents":"(applepie.pro)","link":"https://news.hada.io/topic?id=6941","retrieved":1657340461751}]}